<?xml version="1.0" encoding="UTF-8" ?><panorama><data_properties image_width="13312" image_height="6656" tile_width="512" tile_height="512" image_date="2015-07" pano_id="GIwDCwB6pG8phQrAsrz8kw" imagery_type="1" num_zoom_levels="5" lat="37.794960" lng="-122.400712" original_lat="37.794955" original_lng="-122.400687" elevation_wgs84_m="-22.184178" elevation_egm96_m="10.021980"><copyright>© 2016 Google</copyright><text>428 Clay St</text><street_range>428</street_range><region>San Francisco, California</region><country>United States</country></data_properties><projection_properties projection_type="spherical" pano_yaw_deg="81.119995" tilt_yaw_deg="-150.95" tilt_pitch_deg="1.4399999"/><annotation_properties><link yaw_deg="261.06" pano_id="wIk6eFZuiE563fXJFwA5wA" road_argb="0x80fdf872"><link_text>Clay St</link_text></link><link yaw_deg="81.42" pano_id="vjc37n3KvRtHYauWs8FKBA" road_argb="0x80fdf872"><link_text>Clay St</link_text></link></annotation_properties></panorama>